{"box_data": [{"position": {"minX": 441.75, "minY": 160.0, "maxX": 446.75, "maxY": 165.25}, "class_id": 0, "box_caption": "d 0.783", "scores": {"class_score": 0.783203125}, "domain": "pixel"}, {"position": {"minX": 161.0, "minY": 234.5, "maxX": 166.5, "maxY": 239.75}, "class_id": 0, "box_caption": "d 0.777", "scores": {"class_score": 0.77685546875}, "domain": "pixel"}, {"position": {"minX": 258.0, "minY": 200.75, "maxX": 263.5, "maxY": 206.25}, "class_id": 0, "box_caption": "d 0.772", "scores": {"class_score": 0.77197265625}, "domain": "pixel"}, {"position": {"minX": 411.75, "minY": 195.375, "maxX": 417.25, "maxY": 200.875}, "class_id": 0, "box_caption": "d 0.769", "scores": {"class_score": 0.7685546875}, "domain": "pixel"}, {"position": {"minX": 179.75, "minY": 139.5, "maxX": 185.25, "maxY": 145.0}, "class_id": 0, "box_caption": "d 0.769", "scores": {"class_score": 0.7685546875}, "domain": "pixel"}, {"position": {"minX": 332.75, "minY": 326.25, "maxX": 338.25, "maxY": 331.75}, "class_id": 0, "box_caption": "d 0.768", "scores": {"class_score": 0.76806640625}, "domain": "pixel"}, {"position": {"minX": 326.75, "minY": 235.25, "maxX": 331.75, "maxY": 240.5}, "class_id": 0, "box_caption": "d 0.764", "scores": {"class_score": 0.76416015625}, "domain": "pixel"}, {"position": {"minX": 309.25, "minY": 224.125, "maxX": 314.75, "maxY": 229.625}, "class_id": 0, "box_caption": "d 0.764", "scores": {"class_score": 0.763671875}, "domain": "pixel"}, {"position": {"minX": 150.625, "minY": 266.75, "maxX": 155.875, "maxY": 271.75}, "class_id": 0, "box_caption": "d 0.763", "scores": {"class_score": 0.76318359375}, "domain": "pixel"}, {"position": {"minX": 451.75, "minY": 241.875, "maxX": 457.25, "maxY": 247.125}, "class_id": 0, "box_caption": "d 0.759", "scores": {"class_score": 0.75927734375}, "domain": "pixel"}, {"position": {"minX": 183.75, "minY": 50.75, "maxX": 189.0, "maxY": 55.9375}, "class_id": 0, "box_caption": "d 0.745", "scores": {"class_score": 0.7451171875}, "domain": "pixel"}, {"position": {"minX": 142.375, "minY": 47.59375, "maxX": 147.375, "maxY": 52.46875}, "class_id": 0, "box_caption": "d 0.742", "scores": {"class_score": 0.7421875}, "domain": "pixel"}, {"position": {"minX": 142.0, "minY": 289.25, "maxX": 147.25, "maxY": 294.75}, "class_id": 0, "box_caption": "d 0.742", "scores": {"class_score": 0.74169921875}, "domain": "pixel"}, {"position": {"minX": 308.0, "minY": 375.5, "maxX": 313.5, "maxY": 381.0}, "class_id": 0, "box_caption": "d 0.735", "scores": {"class_score": 0.73486328125}, "domain": "pixel"}, {"position": {"minX": 193.375, "minY": 49.65625, "maxX": 198.875, "maxY": 55.03125}, "class_id": 0, "box_caption": "d 0.720", "scores": {"class_score": 0.72021484375}, "domain": "pixel"}, {"position": {"minX": 134.25, "minY": 195.625, "maxX": 139.75, "maxY": 201.125}, "class_id": 0, "box_caption": "d 0.711", "scores": {"class_score": 0.7109375}, "domain": "pixel"}, {"position": {"minX": 117.4375, "minY": 108.5625, "maxX": 122.8125, "maxY": 113.8125}, "class_id": 0, "box_caption": "d 0.698", "scores": {"class_score": 0.69775390625}, "domain": "pixel"}, {"position": {"minX": 132.625, "minY": 116.5625, "maxX": 138.125, "maxY": 121.8125}, "class_id": 0, "box_caption": "d 0.673", "scores": {"class_score": 0.67333984375}, "domain": "pixel"}, {"position": {"minX": 430.25, "minY": 369.75, "maxX": 435.25, "maxY": 374.75}, "class_id": 0, "box_caption": "d 0.673", "scores": {"class_score": 0.67333984375}, "domain": "pixel"}, {"position": {"minX": 96.1875, "minY": 55.90625, "maxX": 100.8125, "maxY": 60.59375}, "class_id": 0, "box_caption": "d 0.010", "scores": {"class_score": 0.01015472412109375}, "domain": "pixel"}, {"position": {"minX": 97.625, "minY": 46.90625, "maxX": 102.25, "maxY": 52.34375}, "class_id": 0, "box_caption": "d 0.010", "scores": {"class_score": 0.010009765625}, "domain": "pixel"}, {"position": {"minX": 178.0, "minY": 137.875, "maxX": 186.5, "maxY": 146.625}, "class_id": 0, "box_caption": "d 0.005", "scores": {"class_score": 0.004634857177734375}, "domain": "pixel"}, {"position": {"minX": 439.75, "minY": 157.75, "maxX": 448.25, "maxY": 167.0}, "class_id": 0, "box_caption": "d 0.005", "scores": {"class_score": 0.0045166015625}, "domain": "pixel"}, {"position": {"minX": 305.75, "minY": 373.25, "maxX": 314.25, "maxY": 382.75}, "class_id": 0, "box_caption": "d 0.005", "scores": {"class_score": 0.004512786865234375}, "domain": "pixel"}, {"position": {"minX": 105.8125, "minY": 48.1875, "maxX": 110.1875, "maxY": 53.0625}, "class_id": 0, "box_caption": "d 0.005", "scores": {"class_score": 0.0045013427734375}, "domain": "pixel"}, {"position": {"minX": 257.0, "minY": 198.375, "maxX": 264.5, "maxY": 207.875}, "class_id": 0, "box_caption": "d 0.004", "scores": {"class_score": 0.00439453125}, "domain": "pixel"}, {"position": {"minX": 427.75, "minY": 367.75, "maxX": 437.25, "maxY": 377.25}, "class_id": 0, "box_caption": "d 0.004", "scores": {"class_score": 0.00414276123046875}, "domain": "pixel"}, {"position": {"minX": 132.25, "minY": 193.25, "maxX": 140.5, "maxY": 203.0}, "class_id": 0, "box_caption": "d 0.004", "scores": {"class_score": 0.004062652587890625}, "domain": "pixel"}, {"position": {"minX": 450.25, "minY": 240.5, "maxX": 459.25, "maxY": 249.0}, "class_id": 0, "box_caption": "d 0.004", "scores": {"class_score": 0.00399017333984375}, "domain": "pixel"}, {"position": {"minX": 139.75, "minY": 288.0, "maxX": 149.25, "maxY": 296.5}, "class_id": 0, "box_caption": "d 0.004", "scores": {"class_score": 0.003986358642578125}, "domain": "pixel"}, {"position": {"minX": 331.5, "minY": 325.0, "maxX": 340.0, "maxY": 334.0}, "class_id": 0, "box_caption": "d 0.004", "scores": {"class_score": 0.003948211669921875}, "domain": "pixel"}, {"position": {"minX": 307.25, "minY": 223.0, "maxX": 316.75, "maxY": 231.5}, "class_id": 0, "box_caption": "d 0.004", "scores": {"class_score": 0.003902435302734375}, "domain": "pixel"}, {"position": {"minX": 159.75, "minY": 231.75, "maxX": 167.5, "maxY": 241.5}, "class_id": 0, "box_caption": "d 0.004", "scores": {"class_score": 0.0038089752197265625}, "domain": "pixel"}, {"position": {"minX": 409.75, "minY": 194.0, "maxX": 418.75, "maxY": 202.75}, "class_id": 0, "box_caption": "d 0.004", "scores": {"class_score": 0.0037860870361328125}, "domain": "pixel"}, {"position": {"minX": 325.0, "minY": 233.25, "maxX": 334.0, "maxY": 243.25}, "class_id": 0, "box_caption": "d 0.004", "scores": {"class_score": 0.0037441253662109375}, "domain": "pixel"}, {"position": {"minX": 133.25, "minY": 196.375, "maxX": 139.0, "maxY": 202.125}, "class_id": 0, "box_caption": "d 0.004", "scores": {"class_score": 0.0037364959716796875}, "domain": "pixel"}, {"position": {"minX": 309.25, "minY": 375.25, "maxX": 314.75, "maxY": 380.75}, "class_id": 0, "box_caption": "d 0.004", "scores": {"class_score": 0.0035152435302734375}, "domain": "pixel"}, {"position": {"minX": 148.125, "minY": 263.75, "maxX": 156.875, "maxY": 273.75}, "class_id": 0, "box_caption": "d 0.003", "scores": {"class_score": 0.00341033935546875}, "domain": "pixel"}, {"position": {"minX": 191.875, "minY": 47.15625, "maxX": 199.875, "maxY": 56.34375}, "class_id": 0, "box_caption": "d 0.003", "scores": {"class_score": 0.0033512115478515625}, "domain": "pixel"}, {"position": {"minX": 141.125, "minY": 46.28125, "maxX": 146.875, "maxY": 51.59375}, "class_id": 0, "box_caption": "d 0.003", "scores": {"class_score": 0.0031299591064453125}, "domain": "pixel"}, {"position": {"minX": 140.125, "minY": 45.6875, "maxX": 149.875, "maxY": 55.125}, "class_id": 0, "box_caption": "d 0.003", "scores": {"class_score": 0.003116607666015625}, "domain": "pixel"}, {"position": {"minX": 180.875, "minY": 48.0, "maxX": 190.125, "maxY": 57.625}, "class_id": 0, "box_caption": "d 0.003", "scores": {"class_score": 0.0030307769775390625}, "domain": "pixel"}, {"position": {"minX": 115.1875, "minY": 105.375, "maxX": 123.5625, "maxY": 116.25}, "class_id": 0, "box_caption": "d 0.003", "scores": {"class_score": 0.0030117034912109375}, "domain": "pixel"}, {"position": {"minX": 183.875, "minY": 48.3125, "maxX": 189.625, "maxY": 54.0}, "class_id": 0, "box_caption": "d 0.003", "scores": {"class_score": 0.0028553009033203125}, "domain": "pixel"}, {"position": {"minX": 62.75, "minY": 360.0, "maxX": 69.75, "maxY": 369.5}, "class_id": 0, "box_caption": "d 0.003", "scores": {"class_score": 0.0027103424072265625}, "domain": "pixel"}, {"position": {"minX": 130.375, "minY": 112.9375, "maxX": 138.875, "maxY": 124.3125}, "class_id": 0, "box_caption": "d 0.002", "scores": {"class_score": 0.00235748291015625}, "domain": "pixel"}, {"position": {"minX": 324.5, "minY": 236.125, "maxX": 330.5, "maxY": 241.625}, "class_id": 0, "box_caption": "d 0.002", "scores": {"class_score": 0.0018644332885742188}, "domain": "pixel"}, {"position": {"minX": 435.75, "minY": 152.125, "maxX": 451.75, "maxY": 174.125}, "class_id": 0, "box_caption": "d 0.001", "scores": {"class_score": 0.0014238357543945312}, "domain": "pixel"}, {"position": {"minX": 252.0, "minY": 191.75, "maxX": 268.0, "maxY": 215.0}, "class_id": 0, "box_caption": "d 0.001", "scores": {"class_score": 0.0014181137084960938}, "domain": "pixel"}, {"position": {"minX": 187.25, "minY": 40.65625, "maxX": 204.0, "maxY": 62.34375}, "class_id": 0, "box_caption": "d 0.001", "scores": {"class_score": 0.001338958740234375}, "domain": "pixel"}, {"position": {"minX": 156.125, "minY": 225.75, "maxX": 171.125, "maxY": 246.5}, "class_id": 0, "box_caption": "d 0.001", "scores": {"class_score": 0.0013284683227539062}, "domain": "pixel"}, {"position": {"minX": 12.5625, "minY": -1.0859375, "maxX": 17.71875, "maxY": 14.8359375}, "class_id": 0, "box_caption": "d 0.001", "scores": {"class_score": 0.0012674331665039062}, "domain": "pixel"}, {"position": {"minX": 404.25, "minY": 184.875, "maxX": 420.75, "maxY": 207.625}, "class_id": 0, "box_caption": "d 0.001", "scores": {"class_score": 0.0012197494506835938}, "domain": "pixel"}, {"position": {"minX": 443.25, "minY": 231.5, "maxX": 461.25, "maxY": 256.0}, "class_id": 0, "box_caption": "d 0.001", "scores": {"class_score": 0.0011854171752929688}, "domain": "pixel"}, {"position": {"minX": 172.375, "minY": 129.0, "maxX": 188.375, "maxY": 151.75}, "class_id": 0, "box_caption": "d 0.001", "scores": {"class_score": 0.0011816024780273438}, "domain": "pixel"}, {"position": {"minX": 195.125, "minY": 267.75, "maxX": 200.875, "maxY": 273.25}, "class_id": 0, "box_caption": "d 0.001", "scores": {"class_score": 0.0011730194091796875}, "domain": "pixel"}, {"position": {"minX": 136.375, "minY": 283.25, "maxX": 156.875, "maxY": 299.25}, "class_id": 0, "box_caption": "d 0.001", "scores": {"class_score": 0.0011091232299804688}, "domain": "pixel"}, {"position": {"minX": 145.625, "minY": 258.75, "maxX": 163.625, "maxY": 276.75}, "class_id": 0, "box_caption": "d 0.001", "scores": {"class_score": 0.0010786056518554688}, "domain": "pixel"}, {"position": {"minX": 429.0, "minY": 369.0, "maxX": 434.0, "maxY": 374.0}, "class_id": 0, "box_caption": "d 0.001", "scores": {"class_score": 0.0010557174682617188}, "domain": "pixel"}, {"position": {"minX": 453.0, "minY": 242.375, "maxX": 458.5, "maxY": 247.875}, "class_id": 0, "box_caption": "d 0.001", "scores": {"class_score": 0.0010194778442382812}, "domain": "pixel"}], "class_labels": {"0": "d"}}